tokenize_uk/__init__.py
tokenize_uk/tokenize_uk.py
tokenize_uk-0.1.5.dist-info/DESCRIPTION.rst
tokenize_uk-0.1.5.dist-info/METADATA
tokenize_uk-0.1.5.dist-info/RECORD
tokenize_uk-0.1.5.dist-info/WHEEL
tokenize_uk-0.1.5.dist-info/metadata.json
tokenize_uk-0.1.5.dist-info/top_level.txt
