Metadata-Version: 2.0
Name: tokenize-uk
Version: 0.1.5
Summary: Simple python lib to tokenize texts into sentences and sentences to words. Small, fast and robust. Comes with ukrainian flavour 
Home-page: https://github.com/lang-uk/tokenize-uk
Author: Vsevolod Dyomkin, Dmitry Chaplinsky
Author-email: chaplinsky.dmitry@gmail.com
License: MIT
Keywords: tokenize_uk
Platform: UNKNOWN
Classifier: Development Status :: 2 - Pre-Alpha
Classifier: Intended Audience :: Developers
Classifier: License :: OSI Approved :: MIT License
Classifier: Natural Language :: English
Classifier: Programming Language :: Python :: 2
Classifier: Programming Language :: Python :: 2.6
Classifier: Programming Language :: Python :: 2.7
Classifier: Programming Language :: Python :: Implementation :: PyPy
Classifier: Programming Language :: Python :: 3
Classifier: Programming Language :: Python :: 3.3
Classifier: Programming Language :: Python :: 3.4
Classifier: Programming Language :: Python :: 3.5
Requires-Dist: six
